bedrock_agent/__init__.py
bedrock_agent/middleware.py
lwa_fastapi_middleware_bedrock_agent-0.0.4.dist-info/LICENSE
lwa_fastapi_middleware_bedrock_agent-0.0.4.dist-info/METADATA
lwa_fastapi_middleware_bedrock_agent-0.0.4.dist-info/WHEEL
lwa_fastapi_middleware_bedrock_agent-0.0.4.dist-info/top_level.txt
lwa_fastapi_middleware_bedrock_agent-0.0.4.dist-info/RECORD
