Metadata-Version: 2.1
Name: lwa_fastapi_middleware_bedrock_agent
Version: 0.0.4
Summary: FastAPI Middleware for Agents for Amazon Bedrock. Use with AWS Lambda Web Adapter.
Author-email: moritalous <moritalous@gmail.com>
Project-URL: Homepage, https://github.com/moritalous/lwa-fastapi-middleware-bedrock-agent
Project-URL: Issues, https://github.com/moritalous/lwa-fastapi-middleware-bedrock-agent/issues
Classifier: Programming Language :: Python :: 3
Classifier: License :: OSI Approved :: MIT License
Classifier: Operating System :: OS Independent
Requires-Python: >=3.8
License-File: LICENSE
